LICENSE
partial/__init__.py
partial/partial.py
partial/placeholder.py
partial/py.typed
python3_partial-0.0.1.dist-info/LICENSE
python3_partial-0.0.1.dist-info/METADATA
python3_partial-0.0.1.dist-info/WHEEL
python3_partial-0.0.1.dist-info/RECORD
